dojo/__init__.py
dojo/activations.py
dojo/exceptions.py
dojo/losses.py
dojo/misc.py
dojo/optimizers.py
dojo/regularizers.py
dojo/anomaly/__init__.py
dojo/anomaly/algorithms.py
dojo/base/__init__.py
dojo/base/classifier.py
dojo/base/clustering.py
dojo/base/error.py
dojo/base/model.py
dojo/base/preprocessor.py
dojo/base/regressor.py
dojo/bayes/__init__.py
dojo/bayes/naive_bayes.py
dojo/cluster/__init__.py
dojo/cluster/hierarchical.py
dojo/cluster/kmeans.py
dojo/dimred/__init__.py
dojo/dimred/lda.py
dojo/dimred/pca.py
dojo/dimred/utils.py
dojo/ensemble/__init__.py
dojo/ensemble/ada_boost.py
dojo/ensemble/stacking.py
dojo/linear/__init__.py
dojo/linear/lasso.py
dojo/linear/linear_regression.py
dojo/linear/logistic_regression.py
dojo/linear/ridge.py
dojo/metrics/__init__.py
dojo/metrics/classification.py
dojo/metrics/regression.py
dojo/metrics/utils.py
dojo/nlp/__init__.py
dojo/nlp/tf_idf.py
dojo/nn/__init__.py
dojo/nn/layers.py
dojo/nn/neural_network.py
dojo/plot/__init__.py
dojo/plot/decision.py
dojo/preprocessing/__init__.py
dojo/preprocessing/label_encoder.py
dojo/preprocessing/normalizer.py
dojo/preprocessing/one_hot.py
dojo/recommender/__init__.py
dojo/recommender/algorithms.py
dojo/recommender/users.py
dojo/split/__init__.py
dojo/split/batch.py
dojo/split/cross_validate.py
dojo/split/kfolds.py
dojo/split/train_test.py
dojo/split/utils.py
dojo/svm/__init__.py
dojo/svm/utils.py
dojo/svm/classification/__init__.py
dojo/svm/classification/nusvc.py
dojo/svm/classification/svc.py
dojo/svm/libsvm/__init__.py
dojo/svm/libsvm/commonutil.py
dojo/svm/libsvm/libsvm.py
dojo/svm/libsvm/libsvm_win.py
dojo/svm/libsvm/svm.py
dojo/svm/libsvm/svmutil.py
dojo/svm/regression/__init__.py
dojo/svm/regression/nusvr.py
dojo/svm/regression/svr.py
dojo/tree/__init__.py
dojo/tree/classification.py
dojo/tree/extra_classification.py
dojo/tree/extra_regression.py
dojo/tree/regression.py
dojo/tree/utils/__init__.py
dojo/tree/utils/functions.py
dojo/tree/utils/impurity_measurements.py
PyDojoML-0.4.5.dist-info/LICENSE
PyDojoML-0.4.5.dist-info/METADATA
PyDojoML-0.4.5.dist-info/WHEEL
PyDojoML-0.4.5.dist-info/top_level.txt
PyDojoML-0.4.5.dist-info/RECORD
