Metadata-Version: 2.1
Name: PyDojoML
Version: 0.4.5
Summary: A General Purpose Machine Learning Library for Python
Home-page: https://github.com/VIVelev/PyDojoML
Author: Victor Velev
Author-email: velev.victor@yahoo.com
License: UNKNOWN
Platform: UNKNOWN
Classifier: Programming Language :: Python :: 3
Classifier: License :: OSI Approved :: MIT License
Classifier: Operating System :: OS Independent
Requires-Dist: numpy
Requires-Dist: scipy
Requires-Dist: matplotlib
Requires-Dist: progressbar
Requires-Dist: terminaltables
